dset.py
dset-0.0.1.dist-info/LICENSE
dset-0.0.1.dist-info/METADATA
dset-0.0.1.dist-info/WHEEL
dset-0.0.1.dist-info/top_level.txt
dset-0.0.1.dist-info/RECORD
