Metadata-Version: 2.1
Name: dset
Version: 0.0.1
Summary: Disjoint-Set implementation with heuristic optimizations (union-by-rank and path-compression)
Home-page: https://github.com/Mr-Io/dset
Author: Mr-Io
Author-email: mrio.dev@gmail.com
License: UNKNOWN
Project-URL: Bug Reports, https://github.com/Mr-Io/dset/issues
Project-URL: Source, https://github.com/Mr-Io/dset
Platform: UNKNOWN
Classifier: Development Status :: 5 - Production/Stable
Classifier: Intended Audience :: Developers
Classifier: Intended Audience :: Science/Research
Classifier: Topic :: Software Development :: Build Tools
Classifier: Topic :: Scientific/Engineering
Classifier: License :: OSI Approved :: MIT License
Classifier: Programming Language :: Python :: 3 :: Only
Classifier: Programming Language :: Python :: 3.7
Requires-Python: >=3.7
